bfftree/__init__.py
bfftree/bettertree_pb2.py
bfftree/cli.py
bfftree/inputs.py
bfftree/tree.py
bfftree/tests/__init__.py
bfftree/tests/test_radix_tree.py
bfftree-0.1.0.dist-info/METADATA
bfftree-0.1.0.dist-info/WHEEL
bfftree-0.1.0.dist-info/entry_points.txt
bfftree-0.1.0.dist-info/top_level.txt
bfftree-0.1.0.dist-info/RECORD
